{"trial_id": "06", "hyperparameters": {"space": [{"class_name": "Int", "config": {"name": "num_layers", "default": null, "conditions": [], "min_value": 2, "max_value": 5, "step": 1, "sampling": "linear"}}, {"class_name": "Int", "config": {"name": "units0", "default": null, "conditions": [], "min_value": 2, "max_value": 100, "step": 3, "sampling": "linear"}}, {"class_name": "Float", "config": {"name": "dropout0", "default": 0.1, "conditions": [], "min_value": 0.1, "max_value": 0.5, "step": null, "sampling": "linear"}}, {"class_name": "Int", "config": {"name": "units1", "default": null, "conditions": [], "min_value": 2, "max_value": 100, "step": 3, "sampling": "linear"}}, {"class_name": "Float", "config": {"name": "dropout1", "default": 0.1, "conditions": [], "min_value": 0.1, "max_value": 0.5, "step": null, "sampling": "linear"}}, {"class_name": "Choice", "config": {"name": "learning_rate", "default": 0.1, "conditions": [], "values": [0.1, 0.01, 0.001, 0.0001], "ordered": true}}, {"class_name": "Int", "config": {"name": "units2", "default": null, "conditions": [], "min_value": 2, "max_value": 100, "step": 3, "sampling": "linear"}}, {"class_name": "Float", "config": {"name": "dropout2", "default": 0.1, "conditions": [], "min_value": 0.1, "max_value": 0.5, "step": null, "sampling": "linear"}}, {"class_name": "Int", "config": {"name": "units3", "default": null, "conditions": [], "min_value": 2, "max_value": 100, "step": 3, "sampling": "linear"}}, {"class_name": "Float", "config": {"name": "dropout3", "default": 0.1, "conditions": [], "min_value": 0.1, "max_value": 0.5, "step": null, "sampling": "linear"}}, {"class_name": "Int", "config": {"name": "units4", "default": null, "conditions": [], "min_value": 2, "max_value": 100, "step": 3, "sampling": "linear"}}, {"class_name": "Float", "config": {"name": "dropout4", "default": 0.1, "conditions": [], "min_value": 0.1, "max_value": 0.5, "step": null, "sampling": "linear"}}], "values": {"num_layers": 5, "units0": 98, "dropout0": 0.4910740166640517, "units1": 77, "dropout1": 0.3600466606927357, "learning_rate": 0.0001, "units2": 89, "dropout2": 0.1838723917483429, "units3": 38, "dropout3": 0.26892078783969275, "units4": 14, "dropout4": 0.3975074773765438}}, "metrics": {"metrics": {"accuracy": {"direction": "max", "observations": [{"value": [0.7933333516120911], "step": 91}]}, "loss": {"direction": "min", "observations": [{"value": [0.470366895198822], "step": 91}]}, "val_accuracy": {"direction": "max", "observations": [{"value": [0.8888888955116272], "step": 91}]}, "val_loss": {"direction": "min", "observations": [{"value": [0.38048173983891803], "step": 91}]}}}, "score": 0.7933333516120911, "best_step": 91, "status": "COMPLETED", "message": null}